wes_client/__init__.py
wes_client/util.py
wes_client/wes_client_main.py
wes_service/__init__.py
wes_service/arvados_wes.py
wes_service/cwl_runner.py
wes_service/toil_wes.py
wes_service/util.py
wes_service/wes_service_main.py
wes_service/openapi/workflow_execution_service.swagger.yaml
wes_service-5.0.dist-info/licenses/LICENSE
wes_service-5.0.dist-info/METADATA
wes_service-5.0.dist-info/WHEEL
wes_service-5.0.dist-info/entry_points.txt
wes_service-5.0.dist-info/top_level.txt
wes_service-5.0.dist-info/RECORD
