Metadata-Version: 2.4
Name: wes-service
Version: 5.0
Summary: GA4GH Workflow Execution Service reference implementation
Author-email: GA4GH Containers and Workflows task team <common-workflow-language@googlegroups.com>
License-Expression: Apache-2.0
Project-URL: Homepage, https://github.com/common-workflow-language/cwltool-service
Project-URL: Download, https://github.com/common-workflow-language/cwltool-service/releases
Project-URL: Bug Tracker, https://github.com/common-workflow-language/cwltool-service/issues
Platform: "MacOS X"
Platform: "Posix"
Classifier: Intended Audience :: Developers
Classifier: Operating System :: MacOS :: MacOS X
Classifier: Operating System :: POSIX
Classifier: Programming Language :: Python
Classifier: Programming Language :: Python :: 3.9
Classifier: Programming Language :: Python :: 3.10
Classifier: Programming Language :: Python :: 3.11
Classifier: Programming Language :: Python :: 3.12
Classifier: Topic :: Software Development :: Libraries :: Python Modules
Requires-Python: >=3.9
License-File: LICENSE
Requires-Dist: connexion[flask,swagger-ui,uvicorn]<4,>=3
Requires-Dist: ruamel.yaml>=0.15.78
Requires-Dist: schema-salad
Provides-Extra: cwltool
Requires-Dist: cwlref-runner; extra == "cwltool"
Provides-Extra: arvados
Requires-Dist: arvados-cwl-runner; extra == "arvados"
Provides-Extra: toil
Requires-Dist: toil[cwl]==8.2.0; extra == "toil"
Dynamic: license-file
